demo_greeter_pkg/__init__.py
demo_greeter_pkg/greet.py
demo_greeter_pkg_peter-0.1.0.dist-info/licenses/LICENSE
demo_greeter_pkg_peter-0.1.0.dist-info/licenses/LICENSE:Zone.Identifier
demo_greeter_pkg_peter-0.1.0.dist-info/METADATA
demo_greeter_pkg_peter-0.1.0.dist-info/WHEEL
demo_greeter_pkg_peter-0.1.0.dist-info/entry_points.txt
demo_greeter_pkg_peter-0.1.0.dist-info/top_level.txt
demo_greeter_pkg_peter-0.1.0.dist-info/RECORD
